NNimaker/__init__.py
NNimaker/read_qe_outputs.py
NNimaker-4.0.dist-info/METADATA
NNimaker-4.0.dist-info/WHEEL
NNimaker-4.0.dist-info/entry_points.txt
NNimaker-4.0.dist-info/top_level.txt
NNimaker-4.0.dist-info/RECORD
