Metadata-Version: 2.1
Name: NNimaker
Version: 4.0
Summary: A module for processing user data to NN input
Home-page: https://gitlab.hpc.cineca.it/msafari1/nnimaker.git
Author: Mandana Safari
Author-email: m.safari@cineca.it
License: UNKNOWN
Platform: UNKNOWN
